solana_tx_parser-0.0.5.dist-info/METADATA
solana_tx_parser-0.0.5.dist-info/WHEEL
solana_tx_parser-0.0.5.dist-info/entry_points.txt
solana_tx_parser/__init__.py
solana_tx_parser/lib/libsoltxparser.dylib
solana_tx_parser/lib/libsoltxparser.so
solana_tx_parser/lib/soltxparser.dll
solana_tx_parser/parser.py
solana_tx_parser-0.0.5.dist-info/RECORD
