Metadata-Version: 2.1
Name: solana-tx-parser
Version: 0.0.5
Summary: Python bindings for Solana Transaction Parser (tx-parser), enabling Python developers to easily parse and analyze Solana blockchain transactions. This package provides a high-performance C-API wrapper around the original Rust implementation, making blockchain data interpretation accessible in Python while maintaining native-like performance.
Author-Email: mkdir700 <mkdir700@gmail.com>
License: MIT
Classifier: Operating System :: MacOS
Classifier: Operating System :: POSIX :: Linux
Classifier: Operating System :: Microsoft :: Windows
Requires-Python: >=3.8
